cif2dist/__init__.py
cif2dist/cli.py
cif2dist/core.py
cif2dist-0.2.2.dist-info/licenses/LICENSE
cif2dist-0.2.2.dist-info/METADATA
cif2dist-0.2.2.dist-info/WHEEL
cif2dist-0.2.2.dist-info/entry_points.txt
cif2dist-0.2.2.dist-info/top_level.txt
cif2dist-0.2.2.dist-info/RECORD
