Metadata-Version: 2.4
Name: CIF2Dist
Version: 0.2.2
Summary: CIF2Dist is a python application to calculate the number and distance of coordination spheres of atoms in a lattice based on a cif.
Author-email: Marco Gurbisz and Tom Foerster <marco.gurbisz@hhu.de>
License: MIT
Project-URL: Homepage, https://github.com/MGurbisz/CIF2Dist
Project-URL: Repository, https://github.com/MGurbisz/CIF2Dist
Requires-Python: >=3.9
License-File: LICENSE
Requires-Dist: numpy
Requires-Dist: pymatgen
Dynamic: license-file
